doks/__init__.py
doks/__main__.py
doks/doks.py
doks/extract_shields.py
doks/from_command.py
doks/from_file.py
doks/shields.py
doks/variables.py
doks-1.0.1.data/data/shields.yml
doks-1.0.1.data/scripts/doks
doks-1.0.1.dist-info/LICENSE
doks-1.0.1.dist-info/METADATA
doks-1.0.1.dist-info/WHEEL
doks-1.0.1.dist-info/top_level.txt
doks-1.0.1.dist-info/RECORD
