Metadata-Version: 2.1
Name: doks
Version: 1.0.1
Summary: Automatically generated READMEs
Home-page: https://github.com/rec/doks
Author: Tom Ritchford
Author-email: tom@swirly.com
License: MIT
Keywords: documentation
Platform: UNKNOWN
Classifier: Development Status :: 4 - Beta
Classifier: Programming Language :: Python :: 3.6
Classifier: Programming Language :: Python :: 3.7
Classifier: Programming Language :: Python :: 3.8
Classifier: Programming Language :: Python :: 3.9
Classifier: Intended Audience :: Developers
Classifier: License :: OSI Approved :: MIT License
Classifier: Topic :: Software Development :: Libraries
Classifier: Topic :: Utilities
Requires-Dist: impall
Requires-Dist: pyyaml
Requires-Dist: readme-renderer
Requires-Dist: safer
Requires-Dist: toml
